{"photos": [{"imageKey": "1018", "imageSrc": "/20170125_26/apt_realimage_14853318190970X4Qy_JPEG/d8cee2a1b036369ca5cadaa6fcb6b670.jpg", "imageId": "21656@20170125171018608801", "newOldGbn": "NEW", "smallCategoryName": "\uc804\uacbd", "explaination": "\ub4f1\ucd0c\ub3d9 \ud0dc\uc9c4\uc544\ub984 \uc544\ud30c\ud2b8 \uc785\ub2c8\ub2e4. \uc544\ud30c\ud2b8\ub294 \ucd1d 3\uac1c\ub3d9 221\uc138\ub300\ub85c \uc774\ub8e8\uc5b4\uc838 \uc788\uc2b5\ub2c8\ub2e4. \uc544\ud30c\ud2b8 \uc8fc\ubcc0\uc73c\ub85c \uad50\uc721\uc2dc\uc124 (\ucd08, \uc911\ud559\uad50) \ubc0f \ub300\uc911\uad50\ud1b5 ( \ubc84\uc2a4\uc815\ub958\uc7a5, \uc9c0\ud558\ucca0 9\ud638\uc120 \uc99d\ubbf8\uc5ed )\uc774 \uc788\uc2b5\ub2c8\ub2e4.", "registYmdt": "20170125170500", "imageOrder": 0}, {"imageKey": "1018", "imageSrc": "/20170125_108/apt_realimage_1485331821460D4hGr_JPEG/42dc6bfd560904b5c86193845fc7105c.jpg", "imageId": "21658@20170125171021037870", "newOldGbn": "NEW", "smallCategoryName": "\uc815\ubb38", "explaination": "\ub4f1\ucd0c\ub3d9 \ud0dc\uc9c4\uc544\ub984 \uc544\ud30c\ud2b8 \uc815\ubb38\uc785\ub2c8\ub2e4. \uc544\ud30c\ud2b8 \uc815\ubb38\uc73c\ub85c \ucd9c\uc785\uc774 \uac00\ub2a5\ud558\uba70, \uc815\ubb38\uc5d0\ub294 \uacbd\ube44\uc2e4\uc774 \uc704\uce58\ud574 \uc788\uc2b5\ub2c8\ub2e4. \uc678\ubd80\uc778 \ubc0f \uc678\ubd80\ucc28\ub7c9\uc740 \uacbd\ube44\uc2e4\uc744 \ud1b5\ud574 \ub2e8\uc9c0 \uc548\uc73c\ub85c \uc9c4\uc785 \ud560 \uc218 \uc788\uc2b5\ub2c8\ub2e4.", "registYmdt": "20170125170500", "imageOrder": 0}, {"imageKey": "1018", "imageSrc": "/20170125_198/apt_realimage_14853318209537n0c7_JPEG/8da2a05c6c47f72e3d252391ee8c7c2a.jpg", "imageId": "21660@20170125171020475356", "newOldGbn": "NEW", "smallCategoryName": "\uc815\ubb38", "explaination": "\ub4f1\ucd0c\ub3d9 \ud0dc\uc9c4\uc544\ub984 \uc544\ud30c\ud2b8 \uc815\ubb38\uc785\ub2c8\ub2e4. \uc544\ud30c\ud2b8 \uc815\ubb38\uc73c\ub85c \ucd9c\uc785\uc774 \uac00\ub2a5\ud558\uba70, \uc815\ubb38\uc5d0\ub294 \uacbd\ube44\uc2e4\uc774 \uc704\uce58\ud574 \uc788\uc2b5\ub2c8\ub2e4. \uc678\ubd80\uc778 \ubc0f \uc678\ubd80\ucc28\ub7c9\uc740 \uacbd\ube44\uc2e4\uc744 \ud1b5\ud574 \ub2e8\uc9c0 \uc548\uc73c\ub85c \uc9c4\uc785 \ud560 \uc218 \uc788\uc2b5\ub2c8\ub2e4.", "registYmdt": "20170125170500", "imageOrder": 0}, {"imageKey": "1018", "imageSrc": "/20170125_215/apt_realimage_1485331820344FpPwg_JPEG/aae9fdc87c0387f8e9cfa74762a63b6c.jpg", "imageId": "21663@20170125171019786815", "newOldGbn": "NEW", "smallCategoryName": "\uc815\ubb38", "explaination": "\ub4f1\ucd0c\ub3d9 \ud0dc\uc9c4\uc544\ub984 \uc544\ud30c\ud2b8 \uc815\ubb38\uc785\ub2c8\ub2e4. \uc544\ud30c\ud2b8 \uc815\ubb38\uc73c\ub85c \ucd9c\uc785\uc774 \uac00\ub2a5\ud558\uba70, \uc815\ubb38\uc5d0\ub294 \uacbd\ube44\uc2e4\uc774 \uc704\uce58\ud574 \uc788\uc2b5\ub2c8\ub2e4. \uc678\ubd80\uc778 \ubc0f \uc678\ubd80\ucc28\ub7c9\uc740 \uacbd\ube44\uc2e4\uc744 \ud1b5\ud574 \ub2e8\uc9c0 \uc548\uc73c\ub85c \uc9c4\uc785 \ud560 \uc218 \uc788\uc2b5\ub2c8\ub2e4.", "registYmdt": "20170125170500", "imageOrder": 0}, {"imageKey": "1018", "imageSrc": "/20170125_103/apt_realimage_1485331819714uCXIL_JPEG/bb10f612def585ef4590332c70c13ddc.jpg", "imageId": "21664@20170125171019182571", "newOldGbn": "NEW", "smallCategoryName": "\ud6c4\ubb38", "explaination": "\ub4f1\ucd0c\ub3d9 \ud0dc\uc9c4\uc544\ub984 \uc544\ud30c\ud2b8 \ud6c4\ubb38\uc785\ub2c8\ub2e4. \ud6c4\ubb38\uc73c\ub85c\ub294 \ubcf4\ud589\uc790 \ucd9c\uc785\uc774 \uac00\ub2a5\ud558\uba70 \ucc28\ub7c9\uc740 \uc815\ubb38\uc744 \ud1b5\ud574 \uc9c4\uc785 \ud560 \uc218 \uc788\uc2b5\ub2c8\ub2e4. \uc815\ubb38\uc5d0\ub294 \uacbd\ube44\uc2e4\uc774 \uc704\uce58\ud574 \uc788\uc2b5\ub2c8\ub2e4. \uc678\ubd80\uc778 \ubc0f \uc678\ubd80\ucc28\ub7c9\uc740 \uacbd\ube44\uc2e4\uc744 \ud1b5\ud574 \ub2e8\uc9c0 \uc548\uc73c\ub85c \uc9c4\uc785 \ud560 \uc218 \uc788\uc2b5\ub2c8\ub2e4.", "registYmdt": "20170125170500", "imageOrder": 0}, {"imageKey": "1018", "imageSrc": "/20170125_176/apt_realimage_1485331818534B5QF8_JPEG/9ccb94b7c63eb30bc19ea450303db7d5.jpg", "imageId": "21654@20170125171018107841", "newOldGbn": "NEW", "smallCategoryName": "\uac74\ubb3c \uc678\uad00", "explaination": "\ub4f1\ucd0c\ub3d9 \ud0dc\uc9c4\uc544\ub984 \uc544\ud30c\ud2b8 \uc785\ub2c8\ub2e4. \uc544\ud30c\ud2b8\ub294 \ucd1d 3\uac1c\ub3d9 221\uc138\ub300\ub85c \uc774\ub8e8\uc5b4\uc838 \uc788\uc2b5\ub2c8\ub2e4. \uc544\ud30c\ud2b8 \uc8fc\ubcc0\uc73c\ub85c \uad50\uc721\uc2dc\uc124 (\ucd08, \uc911\ud559\uad50) \ubc0f \ub300\uc911\uad50\ud1b5 ( \ubc84\uc2a4\uc815\ub958\uc7a5, \uc9c0\ud558\ucca0 9\ud638\uc120 \uc99d\ubbf8\uc5ed )\uc774 \uc788\uc2b5\ub2c8\ub2e4.", "registYmdt": "20170125170500", "imageOrder": 0}, {"imageKey": "1018", "imageSrc": "/20170125_15/apt_realimage_1485331818044hQuKi_JPEG/9b2e4334b127937383fb29381ef40160.jpg", "imageId": "21659@20170125171017624759", "newOldGbn": "NEW", "smallCategoryName": "\uac74\ubb3c \uc678\uad00", "explaination": "\ub4f1\ucd0c\ub3d9 \ud0dc\uc9c4\uc544\ub984 \uc544\ud30c\ud2b8 \uc785\ub2c8\ub2e4. \uc544\ud30c\ud2b8\ub294 \ucd1d 3\uac1c\ub3d9 221\uc138\ub300\ub85c \uc774\ub8e8\uc5b4\uc838 \uc788\uc2b5\ub2c8\ub2e4. \uc544\ud30c\ud2b8 \uc8fc\ubcc0\uc73c\ub85c \uad50\uc721\uc2dc\uc124 (\ucd08, \uc911\ud559\uad50) \ubc0f \ub300\uc911\uad50\ud1b5 ( \ubc84\uc2a4\uc815\ub958\uc7a5, \uc9c0\ud558\ucca0 9\ud638\uc120 \uc99d\ubbf8\uc5ed )\uc774 \uc788\uc2b5\ub2c8\ub2e4.", "registYmdt": "20170125170500", "imageOrder": 0}, {"imageKey": "1018", "imageSrc": "/20170125_210/apt_realimage_1485331817560OKc1s_JPEG/4c41a1814d3a3be094057cccb2944318.jpg", "imageId": "21665@20170125171017118208", "newOldGbn": "NEW", "smallCategoryName": "1\uce35 \uacf5\uc6a9\ud604\uad00", "explaination": "\ub4f1\ucd0c\ub3d9 \ud0dc\uc9c4\uc544\ub984 \uc544\ud30c\ud2b8 1\uce35 \uacf5\uc6a9\ud604\uad00\uc785\ub2c8\ub2e4. \uc544\ud30c\ud2b8 \ud604\uad00 \uc548\uc73c\ub85c \uacc4\ub2e8\uacfc \uc5d8\ub808\ubca0\uc774\ud130\uac00 \uc124\uce58 \ub418\uc5b4 \uc788\uc5b4 \uac01 \uc138\ub300\ub85c \uc774\ub3d9\ud560 \uc218 \uc788\uc2b5\ub2c8\ub2e4. \ub610\ud55c \uc9c0\uc0c1\uc8fc\ucc28\uc7a5\uc774 \uc798 \ub418\uc5b4 \uc788\uc2b5\ub2c8\ub2e4.", "registYmdt": "20170125170500", "imageOrder": 0}, {"imageKey": "1018", "imageSrc": "/20170125_169/apt_realimage_1485331817041B7bmT_JPEG/e7fbb5dcfc85fc137df092c43f10f319.jpg", "imageId": "21666@20170125171016561192", "newOldGbn": "NEW", "smallCategoryName": "\uc9c0\uc0c1\uc8fc\ucc28\uc7a5", "explaination": "\ub4f1\ucd0c\ub3d9 \ud0dc\uc9c4\uc544\ub984 \uc544\ud30c\ud2b8 \uc9c0\uc0c1\uc8fc\ucc28\uc7a5 \uc785\ub2c8\ub2e4. \uc544\ud30c\ud2b8 \uc815\ubb38\uc73c\ub85c \ucd9c\uc785\uc774 \uac00\ub2a5\ud558\uba70, \uc678\ubd80\uc778 \ubc0f \uc678\ubd80\ucc28\ub7c9\uc740 \uacbd\ube44\uc2e4\uc744 \ud1b5\ud574 \ub2e8\uc9c0 \uc548\uc73c\ub85c \uc9c4\uc785 \ud560 \uc218 \uc788\uc2b5\ub2c8\ub2e4.", "registYmdt": "20170125170500", "imageOrder": 0}, {"imageKey": "1018", "imageSrc": "/20170125_11/apt_realimage_14853318164877ab9f_JPEG/e1784c9693242466a27046820d473592.jpg", "imageId": "21667@20170125171016002676", "newOldGbn": "NEW", "smallCategoryName": "\uc9c0\uc0c1\uc8fc\ucc28\uc7a5", "explaination": "\ub4f1\ucd0c\ub3d9 \ud0dc\uc9c4\uc544\ub984 \uc544\ud30c\ud2b8 \uc9c0\uc0c1\uc8fc\ucc28\uc7a5 \uc785\ub2c8\ub2e4. \uc544\ud30c\ud2b8 \uc815\ubb38\uc73c\ub85c \ucd9c\uc785\uc774 \uac00\ub2a5\ud558\uba70, \uc678\ubd80\uc778 \ubc0f \uc678\ubd80\ucc28\ub7c9\uc740 \uacbd\ube44\uc2e4\uc744 \ud1b5\ud574 \ub2e8\uc9c0 \uc548\uc73c\ub85c \uc9c4\uc785 \ud560 \uc218 \uc788\uc2b5\ub2c8\ub2e4.", "registYmdt": "20170125170500", "imageOrder": 0}, {"imageKey": "1018", "imageSrc": "/20170125_164/apt_realimage_148533181593259cFH_JPEG/d398c3fe73648fcafa755b7342b2fbaf.jpg", "imageId": "21668@20170125171015456052", "newOldGbn": "NEW", "smallCategoryName": "\uc9c0\ud558 \uc8fc\ucc28\uc7a5 \uc785\uad6c", "explaination": "\ub4f1\ucd0c\ub3d9 \ud0dc\uc9c4\uc544\ub984 \uc544\ud30c\ud2b8 \uc9c0\ud558\uc8fc\ucc28\uc7a5 \uc785\uad6c\uc785\ub2c8\ub2e4. \uc544\ud30c\ud2b8 \ub2e8\uc9c0 \uc548\uc73c\ub85c \uc9c0\uc0c1\uc8fc\ucc28\uc7a5\uacfc \uc9c0\ud558\uc8fc\ucc28\uc7a5\uc744 \uc774\uc6a9\ud560 \uc218 \uc788\uc2b5\ub2c8\ub2e4. \uc8fc\ucc28\uc7a5 \uacf5\uac04\uc774 \ub109\ub109\ud558\uc5ec \uc8fc\ucc28\ud558\uae30\uc5d0 \ud3b8\ub9ac\ud569\ub2c8\ub2e4.", "registYmdt": "20170125170500", "imageOrder": 0}, {"imageKey": "1018", "imageSrc": "/20170125_160/apt_realimage_1485331815342ML6OX_JPEG/bb43739961f3c482bd33c71737d1e528.jpg", "imageId": "21669@20170125171014823892", "newOldGbn": "NEW", "smallCategoryName": "\uc9c0\ud558 \uc8fc\ucc28\uc7a5 \uc785\uad6c", "explaination": "\ub4f1\ucd0c\ub3d9 \ud0dc\uc9c4\uc544\ub984 \uc544\ud30c\ud2b8 \uc9c0\ud558\uc8fc\ucc28\uc7a5 \uc785\uad6c\uc785\ub2c8\ub2e4. \uc544\ud30c\ud2b8 \ub2e8\uc9c0 \uc548\uc73c\ub85c \uc9c0\uc0c1\uc8fc\ucc28\uc7a5\uacfc \uc9c0\ud558\uc8fc\ucc28\uc7a5\uc744 \uc774\uc6a9\ud560 \uc218 \uc788\uc2b5\ub2c8\ub2e4. \uc8fc\ucc28\uc7a5 \uacf5\uac04\uc774 \ub109\ub109\ud558\uc5ec \uc8fc\ucc28\ud558\uae30\uc5d0 \ud3b8\ub9ac\ud569\ub2c8\ub2e4.", "registYmdt": "20170125170500", "imageOrder": 0}, {"imageKey": "1018", "imageSrc": "/20170125_130/apt_realimage_1485331814746rBXMr_JPEG/100ad9e1adb4681ece846623628f47d2.jpg", "imageId": "21670@20170125171014315506", "newOldGbn": "NEW", "smallCategoryName": "\uc9c0\ud558 \uc8fc\ucc28\uc7a5", "explaination": "\ub4f1\ucd0c\ub3d9 \ud0dc\uc9c4\uc544\ub984 \uc544\ud30c\ud2b8 \uc9c0\ud558\uc8fc\ucc28\uc7a5 \uc785\ub2c8\ub2e4. \uc544\ud30c\ud2b8 \ub2e8\uc9c0 \uc548\uc73c\ub85c \uc9c0\uc0c1\uc8fc\ucc28\uc7a5\uacfc \uc9c0\ud558\uc8fc\ucc28\uc7a5\uc744 \uc774\uc6a9\ud560 \uc218 \uc788\uc2b5\ub2c8\ub2e4. \uc8fc\ucc28\uc7a5 \uacf5\uac04\uc774 \ub109\ub109\ud558\uc5ec \uc8fc\ucc28\ud558\uae30\uc5d0 \ud3b8\ub9ac\ud569\ub2c8\ub2e4.", "registYmdt": "20170125170500", "imageOrder": 0}, {"imageKey": "1018", "imageSrc": "/20170125_137/apt_realimage_1485331814174y22zd_JPEG/253f2aedb5c49affbeb1213d83383a41.jpg", "imageId": "21671@20170125171013706380", "newOldGbn": "NEW", "smallCategoryName": "\uc9c0\ud558 \uc8fc\ucc28\uc7a5", "explaination": "\ub4f1\ucd0c\ub3d9 \ud0dc\uc9c4\uc544\ub984 \uc544\ud30c\ud2b8 \uc9c0\ud558\uc8fc\ucc28\uc7a5 \uc785\ub2c8\ub2e4. \uc544\ud30c\ud2b8 \ub2e8\uc9c0 \uc548\uc73c\ub85c \uc9c0\uc0c1\uc8fc\ucc28\uc7a5\uacfc \uc9c0\ud558\uc8fc\ucc28\uc7a5\uc744 \uc774\uc6a9\ud560 \uc218 \uc788\uc2b5\ub2c8\ub2e4. \uc8fc\ucc28\uc7a5 \uacf5\uac04\uc774 \ub109\ub109\ud558\uc5ec \uc8fc\ucc28\ud558\uae30\uc5d0 \ud3b8\ub9ac\ud569\ub2c8\ub2e4.", "registYmdt": "20170125170500", "imageOrder": 0}, {"imageKey": "1018", "imageSrc": "/20170125_155/apt_realimage_1485331813609VYM10_JPEG/10e3a2d00a5708d44a18ab2d0ea55419.jpg", "imageId": "21672@20170125171013047816", "newOldGbn": "NEW", "smallCategoryName": "\ub180\uc774\ud130", "explaination": "\ub4f1\ucd0c\ub3d9 \ud0dc\uc9c4\uc544\ub984 \uc544\ud30c\ud2b8 \ub180\uc774\ud130 \uc785\ub2c8\ub2e4. \uc544\ud30c\ud2b8 \uc548\uc73c\ub85c \ub180\uc774\ud130\uac00 \uc704\uce58\ud574 \uc788\uc2b5\ub2c8\ub2e4. \uc544\uc774\ub4e4\uc758 \uc548\uc804\uc744 \uc704\ud574 \ubc14\ub2e5\uc740 \ube14\ub7ed\uc73c\ub85c \uc124\uce58\ub418\uc5b4 \uc788\uc73c\uba70, \uacf5\uac04\uc774 \ub113\uace0, \ub180\uc774\uae30\uad6c\uac00 \uc798 \ubc30\uce58\ub418\uc5b4 \uc788\uc5b4 \uc544\uc774\ub4e4\uc774 \uc548\uc804\ud558\uace0 \uc990\uac81\uac8c \ub6f0\uc5b4 \ub180 \uc218 \uc788\uc2b5\ub2c8\ub2e4", "registYmdt": "20170125170500", "imageOrder": 0}, {"imageKey": "1018", "imageSrc": "/20170125_76/apt_realimage_1485331812925qKkf5_JPEG/4630885fc5b32d98a612c97862b859cb.jpg", "imageId": "21675@20170125171012386615", "newOldGbn": "NEW", "smallCategoryName": "\ub178\uc778\uc815", "explaination": "\ub4f1\ucd0c\ub3d9 \ud0dc\uc9c4\uc544\ub984 \uc544\ud30c\ud2b8 \ub178\uc778\uc815(\uacbd\ub85c\ub2f9)\uc785\ub2c8\ub2e4. \uc544\ud30c\ud2b8 \ub2e8\uc9c0 \uc548\uc73c\ub85c \uac74\ubb3c\uc774 \uc704\uce58\ud574 \uc788\uc2b5\ub2c8\ub2e4. \uc5b4\ub978\ub4e4\uc744 \uc704\ud55c \uc2dc\uc124\uc774 \uac16\ucd94\uc5b4\uc838 \uc788\uc5b4 \uc5b8\uc81c\ub4e0 \ud3b8\ub9ac\ud558\uac8c \uc774\uc6a9\ud560 \uc218 \uc788\uc2b5\ub2c8\ub2e4.", "registYmdt": "20170125170500", "imageOrder": 0}, {"imageKey": "1018", "imageSrc": "/20170125_228/apt_realimage_1485331812286KAnEG_JPEG/6a59b7ec73da66a0c136f4f11b3207a1.jpg", "imageId": "21676@20170125171011762279", "newOldGbn": "NEW", "smallCategoryName": "\uad00\ub9ac\uc0ac\ubb34\uc18c", "explaination": "\ub4f1\ucd0c\ub3d9 \ud0dc\uc9c4\uc544\ub984 \uc544\ud30c\ud2b8 \uad00\ub9ac\uc0ac\ubb34\uc18c\uc785\ub2c8\ub2e4. \uc544\ud30c\ud2b8 \ub2e8\uc9c0 \uc548\uc73c\ub85c \uac74\ubb3c\uc774 \uc704\uce58\ud574 \uc788\uc2b5\ub2c8\ub2e4. \uc8fc\ubbfc\ub4e4\uc774 \uc5b8\uc81c\ub4e0 \ud3b8\ub9ac\ud558\uac8c \uc774\uc6a9\ud560 \uc218 \uc788\ub3c4\ub85d \uc798 \uc900\ube44\ub418\uc5b4 \uc788\uc2b5\ub2c8\ub2e4.", "registYmdt": "20170125170500", "imageOrder": 0}, {"imageKey": "1018", "imageSrc": "/20170125_123/apt_realimage_1485331811641Ku8S2_JPEG/3472ba88b295c18684964926d6fb0d80.jpg", "imageId": "21673@20170125171011069759", "newOldGbn": "NEW", "smallCategoryName": "\uacbd\ube44\uc2e4", "explaination": "\ub4f1\ucd0c\ub3d9 \ud0dc\uc9c4\uc544\ub984 \uc544\ud30c\ud2b8 \uacbd\ube44\uc2e4 \uc785\ub2c8\ub2e4. \uc544\ud30c\ud2b8 \uc815\ubb38 \ubc0f \ub2e8\uc9c0 \uc548\uc73c\ub85c\uacbd\ube44\uc2e4\uc774 \uc704\uce58\ud574 \uc788\uc2b5\ub2c8\ub2e4. \uc678\ubd80\ucc28\ub7c9\uc740 \uc9c4\uc785\uc2dc \uacbd\ube44\uc2e4\uc744 \ud1b5\ud574 \uc9c4\uc785 \ud560 \uc218 \uc788\ub3c4\ub85d \ub418\uc5b4 \uc788\uc2b5\ub2c8\ub2e4.", "registYmdt": "20170125170500", "imageOrder": 0}, {"imageKey": "1018", "imageSrc": "/20170125_26/apt_realimage_1485331810943Vg3MQ_JPEG/25df2511242ddce68be006bb53c8543a.jpg", "imageId": "21674@20170125171010440562", "newOldGbn": "NEW", "smallCategoryName": "\uacbd\ube44\uc2e4", "explaination": "\ub4f1\ucd0c\ub3d9 \ud0dc\uc9c4\uc544\ub984 \uc544\ud30c\ud2b8 \uacbd\ube44\uc2e4 \uc785\ub2c8\ub2e4. \uc544\ud30c\ud2b8 \uc815\ubb38 \ubc0f \ub2e8\uc9c0 \uc548\uc73c\ub85c\uacbd\ube44\uc2e4\uc774 \uc704\uce58\ud574 \uc788\uc2b5\ub2c8\ub2e4. \uc678\ubd80\ucc28\ub7c9\uc740 \uc9c4\uc785\uc2dc \uacbd\ube44\uc2e4\uc744 \ud1b5\ud574 \uc9c4\uc785 \ud560 \uc218 \uc788\ub3c4\ub85d \ub418\uc5b4 \uc788\uc2b5\ub2c8\ub2e4.", "registYmdt": "20170125170500", "imageOrder": 0}, {"imageKey": "1018", "imageSrc": "/20170125_57/apt_realimage_1485331810358BRqBz_JPEG/5410fb5a254a245f7df1f8b55b08997f.jpg", "imageId": "21677@20170125171009853405", "newOldGbn": "NEW", "smallCategoryName": "\uacbd\ube44\uc2e4", "explaination": "\ub4f1\ucd0c\ub3d9 \ud0dc\uc9c4\uc544\ub984 \uc544\ud30c\ud2b8 \uacbd\ube44\uc2e4 \uc785\ub2c8\ub2e4. \uc544\ud30c\ud2b8 \uc815\ubb38 \ubc0f \ub2e8\uc9c0 \uc548\uc73c\ub85c\uacbd\ube44\uc2e4\uc774 \uc704\uce58\ud574 \uc788\uc2b5\ub2c8\ub2e4. \uc678\ubd80\ucc28\ub7c9\uc740 \uc9c4\uc785\uc2dc \uacbd\ube44\uc2e4\uc744 \ud1b5\ud574 \uc9c4\uc785 \ud560 \uc218 \uc788\ub3c4\ub85d \ub418\uc5b4 \uc788\uc2b5\ub2c8\ub2e4.", "registYmdt": "20170125170500", "imageOrder": 0}, {"imageKey": "1018", "imageSrc": "/20170125_89/apt_realimage_14853318097573p0jr_JPEG/2f55a4d4f00443ab5fe0e49ce3f695a7.jpg", "imageId": "21655@20170125171009271241", "newOldGbn": "NEW", "smallCategoryName": "\ub3c4\ubcf4 5\ubd84 \uc774\ub0b4 \ud3b8\uc758\uc2dc\uc124", "explaination": "\ub4f1\ucd0c\ub3d9 \ud0dc\uc9c4\uc544\ub984 \uc544\ud30c\ud2b8 \uc8fc\ubcc0 \ud3b8\uc758\uc2dc\uc124 \uc785\ub2c8\ub2e4. \uc544\ud30c\ud2b8 \uc8fc\ubcc0\uc73c\ub85c \ud3b8\uc758\uc810 \ubc0f \ub9c8\ud2b8\uac00 \uc788\uc5b4 \uc8fc\ubbfc\ub4e4\uc774 \uac00\uae5d\uace0 \ud3b8\ub9ac\ud558\uac8c \ubb3c\uac74\uc744 \uad6c\uc785\ud560 \uc218 \uc788\uc73c\uba70, \ub610\ud55c \uacf5\uc6d0\uc774 \uc788\uc5b4 \uc0b0\ucc45\ud558\uae30\uc5d0 \uc88b\uc2b5\ub2c8\ub2e4.", "registYmdt": "20170125170500", "imageOrder": 0}, {"imageKey": "1018", "imageSrc": "/20170125_75/apt_realimage_1485331809186jpvWW_JPEG/6048dbf4e992f49451357bfd7223c5fd.jpg", "imageId": "21657@20170125171008648140", "newOldGbn": "NEW", "smallCategoryName": "\ub3c4\ubcf4 5\ubd84 \uc774\ub0b4 \ud3b8\uc758\uc2dc\uc124", "explaination": "\ub4f1\ucd0c\ub3d9 \ud0dc\uc9c4\uc544\ub984 \uc544\ud30c\ud2b8 \uc8fc\ubcc0 \ud3b8\uc758\uc2dc\uc124 \uc785\ub2c8\ub2e4. \uc544\ud30c\ud2b8 \uc8fc\ubcc0\uc73c\ub85c \ud3b8\uc758\uc810 \ubc0f \ub9c8\ud2b8\uac00 \uc788\uc5b4 \uc8fc\ubbfc\ub4e4\uc774 \uac00\uae5d\uace0 \ud3b8\ub9ac\ud558\uac8c \ubb3c\uac74\uc744 \uad6c\uc785\ud560 \uc218 \uc788\uc73c\uba70, \ub610\ud55c \uacf5\uc6d0\uc774 \uc788\uc5b4 \uc0b0\ucc45\ud558\uae30\uc5d0 \uc88b\uc2b5\ub2c8\ub2e4.", "registYmdt": "20170125170500", "imageOrder": 0}, {"imageKey": "1018", "imageSrc": "/20170125_12/apt_realimage_1485331808578gyGsB_JPEG/14f14de5febcfd6bbddf82c6bd61afd4.jpg", "imageId": "21661@20170125171007928881", "newOldGbn": "NEW", "smallCategoryName": "\ub3c4\ubcf4 5\ubd84 \uc774\ub0b4 \ud3b8\uc758\uc2dc\uc124", "explaination": "\ub4f1\ucd0c\ub3d9 \ud0dc\uc9c4\uc544\ub984 \uc544\ud30c\ud2b8 \uc8fc\ubcc0 \ud3b8\uc758\uc2dc\uc124 \uc785\ub2c8\ub2e4. \uc544\ud30c\ud2b8 \uc8fc\ubcc0\uc73c\ub85c \ud3b8\uc758\uc810 \ubc0f \ub9c8\ud2b8\uac00 \uc788\uc5b4 \uc8fc\ubbfc\ub4e4\uc774 \uac00\uae5d\uace0 \ud3b8\ub9ac\ud558\uac8c \ubb3c\uac74\uc744 \uad6c\uc785\ud560 \uc218 \uc788\uc73c\uba70, \ub610\ud55c \uacf5\uc6d0\uc774 \uc788\uc5b4 \uc0b0\ucc45\ud558\uae30\uc5d0 \uc88b\uc2b5\ub2c8\ub2e4.", "registYmdt": "20170125170500", "imageOrder": 0}, {"imageKey": "1018", "imageSrc": "/20110422_21/land_system_13034386937030CBOA_JPEG/1120728170107_2.jpg", "imageType": "IA1", "imageId": "1018@20110422111813745020", "etcItem1": "150448", "newOldGbn": "OLD", "smallCategoryName": "", "registYmdt": "20100514180910", "imageOrder": 0}, {"imageKey": "1018", "imageSrc": "/20110422_221/land_system_1303438694733UKFh7_JPEG/1120728170107_6.jpg", "imageType": "IA1", "imageId": "1018@20110422111814778732", "etcItem1": "150452", "newOldGbn": "OLD", "smallCategoryName": "", "registYmdt": "20100514180910", "imageOrder": 0}, {"imageKey": "1018", "imageSrc": "/20110422_143/land_system_1303438694311G7a0a_JPEG/1120728170107_5.jpg", "imageType": "IA1", "imageId": "1018@20110422111814350473", "etcItem1": "150451", "newOldGbn": "OLD", "smallCategoryName": "", "registYmdt": "20100514180910", "imageOrder": 0}, {"imageKey": "1018", "imageSrc": "/20110422_44/land_system_1303438693521boRlE_JPEG/1120728170107_1.jpg", "imageType": "IA1", "imageId": "1018@20110422111813562387", "etcItem1": "150447", "newOldGbn": "OLD", "smallCategoryName": "", "registYmdt": "20100514180910", "imageOrder": 0}, {"imageKey": "1018", "imageSrc": "/20110422_3/land_system_1303438694097a5HHj_JPEG/1120728170107_4.jpg", "imageType": "IA3", "imageId": "1018@20110422111814140205", "etcItem1": "150450", "newOldGbn": "OLD", "smallCategoryName": "", "registYmdt": "20100514180910", "imageOrder": 0}, {"imageKey": "1018", "imageSrc": "/20110422_147/land_system_1303438693895zck7n_JPEG/1120728170107_3.jpg", "imageType": "IB4", "imageId": "1018@20110422111813934088", "etcItem1": "150449", "newOldGbn": "OLD", "smallCategoryName": "", "registYmdt": "20100514180910", "imageOrder": 0}], "complexDetail": {"complexNo": "1018", "complexName": "\ud0dc\uc9c4\uc544\ub984", "cortarNo": "1150010200", "realEstateTypeCode": "APT", "realEstateTypeName": "\uc544\ud30c\ud2b8", "detailAddress": "676", "roadAddress": "\ub4f1\ucd0c\ub85c53\uae38 39", "latitude": 37.5496, "longitude": 126.86106, "totalHouseholdCount": 221, "totalLeaseHouseholdCount": 0, "permanentLeaseHouseholdCount": 0, "nationLeaseHouseholdCount": 0, "civilLeaseHouseholdCount": 0, "publicLeaseHouseholdCount": 0, "longTermLeaseHouseholdCount": 0, "etcLeaseHouseholdCount": 0, "highFloor": 10, "lowFloor": 7, "completionYearMonth": "199509", "totalDongCount": 3, "maxSupplyArea": 145.01, "minSupplyArea": 83.04, "dealCount": 3, "rentCount": 1, "leaseCount": 0, "shortTermRentCount": 0, "isBookmarked": false, "batlRatio": "239", "btlRatio": "33", "parkingCountByHousehold": 0.95, "constructionCompanyName": "\ud0dc\uc9c4\uac74\uc124\u321c", "heatMethodTypeCode": "HT001", "heatFuelTypeCode": "HF001", "pyoengNames": "83\u33a1, 105\u33a1, 145", "managementOfficeTelNo": "02-2646-6152", "buildingRegister": "0evZmKVqAqvI5ZSQJng9V3Ah1PNVHILg", "address": "\uc11c\uc6b8\uc2dc \uac15\uc11c\uad6c \ub4f1\ucd0c\ub3d9", "roadAddressPrefix": "\uc11c\uc6b8\uc2dc \uac15\uc11c\uad6c"}, "complexPyeongDetailList": [{"pyeongNo": "1", "supplyAreaDouble": 83.04, "supplyArea": "83.04", "pyeongName": "83", "supplyPyeong": "25.11", "pyeongName2": "25", "exclusiveArea": "59.94", "exclusivePyeong": "18.13", "householdCountByPyeong": "96", "realEstateTypeCode": "A01", "exclusiveRate": "72", "grandPlanList": [{"imageId": "1018@20110420195339195762", "imageOrder": 0, "imageSrc": "/20120123_298/land_system_1327327614598uK964_JPEG/115_1018_1_82_1276227195864.jpg", "imageType": "1"}], "maintenanceCostList": [{"basisYearMonth": "202006", "totalPrice": "144335"}, {"basisYearMonth": "202005", "totalPrice": "142577"}, {"basisYearMonth": "202004", "totalPrice": "150072"}, {"basisYearMonth": "202003", "totalPrice": "146040"}, {"basisYearMonth": "202002", "totalPrice": "146797"}, {"basisYearMonth": "202001", "totalPrice": "149417"}, {"basisYearMonth": "201912", "totalPrice": "143534"}, {"basisYearMonth": "201911", "totalPrice": "142656"}, {"basisYearMonth": "201910", "totalPrice": "138948"}, {"basisYearMonth": "201909", "totalPrice": "115702"}, {"basisYearMonth": "201908", "totalPrice": "109139"}], "averageMaintenanceCost": {"averageTotalPrice": "139020", "summerTotalPrice": "126737", "winterTotalPrice": "146583"}, "entranceType": "\ubcf5\ub3c4\uc2dd", "landPriceMaxByPtp": {"ptpNo": "1", "supplyArea": "83.04", "totalArea": "83.04", "minPrice": "296000000", "maxPrice": "355000000", "stdYear": 2020, "stdYmd": "20200101", "landPriceTax": {"propertyTotalTax": 721200, "propertyTax": 352500, "localEduTax": 70500, "cityAreaTax": 298200, "realEstateTotalTax": 0, "decisionTax": 0, "ruralSpecialTax": 0}}, "roomCnt": "3", "bathroomCnt": "1"}, {"pyeongNo": "2", "supplyAreaDouble": 105.85, "supplyArea": "105.85", "pyeongName": "105", "supplyPyeong": "32.01", "pyeongName2": "32", "exclusiveArea": "84.81", "exclusivePyeong": "25.65", "householdCountByPyeong": "95", "realEstateTypeCode": "A01", "exclusiveRate": "80", "grandPlanList": [{"imageId": "1018@20110420195339469606", "imageOrder": 1, "imageSrc": "/20120123_207/land_system_1327327615535cmIe1_JPEG/115_1018_2_105_1276227223033.jpg", "imageType": "2"}], "maintenanceCostList": [{"basisYearMonth": "202006", "totalPrice": "204222"}, {"basisYearMonth": "202005", "totalPrice": "201734"}, {"basisYearMonth": "202004", "totalPrice": "212340"}, {"basisYearMonth": "202003", "totalPrice": "206634"}, {"basisYearMonth": "202002", "totalPrice": "207705"}, {"basisYearMonth": "202001", "totalPrice": "211412"}, {"basisYearMonth": "201912", "totalPrice": "203089"}, {"basisYearMonth": "201911", "totalPrice": "201847"}, {"basisYearMonth": "201910", "totalPrice": "196599"}, {"basisYearMonth": "201909", "totalPrice": "163709"}, {"basisYearMonth": "201908", "totalPrice": "154422"}], "averageMaintenanceCost": {"averageTotalPrice": "196701", "summerTotalPrice": "179322", "winterTotalPrice": "207402"}, "articleStatistics": {"pyeongNo": "2", "dealCount": "0", "leaseCount": "0", "rentCount": "1", "shortTermRentCount": "0", "dealPriceString": "", "dealPricePerSpaceString": "", "leasePriceString": "", "leasePricePerSpaceString": "", "leasePriceRateString": "", "rentPriceString": "2\uc5b5/70", "rentDepositPriceMin": "2\uc5b5", "rentPriceMin": "70", "rentDepositPriceMax": "2\uc5b5", "rentPriceMax": "70"}, "entranceType": "\uacc4\ub2e8\uc2dd", "landPriceMaxByPtp": {"ptpNo": "2", "supplyArea": "105.85", "totalArea": "105.85", "minPrice": "351000000", "maxPrice": "418000000", "stdYear": 2020, "stdYmd": "20200101", "landPriceTax": {"propertyTotalTax": 887520, "propertyTax": 447000, "localEduTax": 89400, "cityAreaTax": 351120, "realEstateTotalTax": 0, "decisionTax": 0, "ruralSpecialTax": 0}}, "roomCnt": "3", "bathroomCnt": "2"}, {"pyeongNo": "3", "supplyAreaDouble": 145.01, "supplyArea": "145.01", "pyeongName": "145", "supplyPyeong": "43.86", "pyeongName2": "43", "exclusiveArea": "121.22", "exclusivePyeong": "36.66", "householdCountByPyeong": "30", "realEstateTypeCode": "A01", "exclusiveRate": "84", "grandPlanList": [{"imageId": "1018@20110420195339778093", "imageOrder": 2, "imageSrc": "/20120123_171/land_system_13273276166022glAK_JPEG/115_1018_3_145_1276227230247.jpg", "imageType": "3"}], "maintenanceCostList": [{"basisYearMonth": "202006", "totalPrice": "291897"}, {"basisYearMonth": "202005", "totalPrice": "288341"}, {"basisYearMonth": "202004", "totalPrice": "303500"}, {"basisYearMonth": "202003", "totalPrice": "295344"}, {"basisYearMonth": "202002", "totalPrice": "296875"}, {"basisYearMonth": "202001", "totalPrice": "302174"}, {"basisYearMonth": "201912", "totalPrice": "290278"}, {"basisYearMonth": "201911", "totalPrice": "288502"}, {"basisYearMonth": "201910", "totalPrice": "281002"}, {"basisYearMonth": "201909", "totalPrice": "233991"}, {"basisYearMonth": "201908", "totalPrice": "220717"}], "averageMaintenanceCost": {"averageTotalPrice": "281147", "summerTotalPrice": "256307", "winterTotalPrice": "296442"}, "articleStatistics": {"pyeongNo": "3", "dealCount": "10", "leaseCount": "0", "rentCount": "0", "shortTermRentCount": "0", "dealPriceMin": "8\uc5b5 5,000", "dealPriceMax": "8\uc5b5 8,000", "dealPricePerSpaceMin": "1,938", "dealPricePerSpaceMax": "2,006", "dealPriceString": "8\uc5b5 5,000~8\uc5b5 8,000", "dealPricePerSpaceString": "(1,938~2,006\ub9cc\uc6d0/3.3\u33a1)", "leasePriceString": "", "leasePricePerSpaceString": "", "leasePriceRateString": ""}, "entranceType": "\uacc4\ub2e8\uc2dd", "landPriceMaxByPtp": {"ptpNo": "3", "supplyArea": "145.01", "totalArea": "145.01", "minPrice": "408000000", "maxPrice": "468000000", "stdYear": 2020, "stdYmd": "20200101", "landPriceTax": {"propertyTotalTax": 1019520, "propertyTax": 522000, "localEduTax": 104400, "cityAreaTax": 393120, "realEstateTotalTax": 0, "decisionTax": 0, "ruralSpecialTax": 0}}, "roomCnt": "4", "bathroomCnt": "2"}]}