{"photos": [], "complexDetail": {"complexNo": "104370", "complexName": "\uccad\ub2f4\ubc94\uc2e0\uce7c\ub9ad\uc2a4\ube4c3\ucc28", "cortarNo": "1168010400", "realEstateTypeCode": "APT", "realEstateTypeName": "\uc544\ud30c\ud2b8", "detailAddress": "62-27", "roadAddress": "\ub3c4\uc0b0\ub300\ub85c92\uae38 38", "latitude": 37.522229, "longitude": 127.049228, "totalHouseholdCount": 12, "totalLeaseHouseholdCount": 0, "permanentLeaseHouseholdCount": 0, "nationLeaseHouseholdCount": 0, "civilLeaseHouseholdCount": 0, "publicLeaseHouseholdCount": 0, "longTermLeaseHouseholdCount": 0, "etcLeaseHouseholdCount": 0, "highFloor": 5, "lowFloor": 5, "completionYearMonth": "201112", "totalDongCount": 1, "maxSupplyArea": 55.82, "minSupplyArea": 55.78, "dealCount": 1, "rentCount": 3, "leaseCount": 0, "shortTermRentCount": 0, "isBookmarked": false, "batlRatio": "166", "btlRatio": "49", "parkingCountByHousehold": 0.91, "constructionCompanyName": "\ubc94\uc2e0\uc885\ud569\uac74\uc124(\uc8fc)", "heatMethodTypeCode": "HT001", "heatFuelTypeCode": "HF001", "pyoengNames": "55A\u33a1, 55B\u33a1, 55C", "buildingRegister": "TIogTMnE2rBWT4PmVVsHHsm2Fbi3VQN4", "address": "\uc11c\uc6b8\uc2dc \uac15\ub0a8\uad6c \uccad\ub2f4\ub3d9", "roadAddressPrefix": "\uc11c\uc6b8\uc2dc \uac15\ub0a8\uad6c"}, "complexPyeongDetailList": [{"pyeongNo": "1", "supplyAreaDouble": 55.78, "supplyArea": "55.78", "pyeongName": "55A", "supplyPyeong": "16.87", "pyeongName2": "16A", "exclusiveArea": "45.31", "exclusivePyeong": "13.7", "householdCountByPyeong": "4", "realEstateTypeCode": "A01", "exclusiveRate": "81", "entranceType": "\uacc4\ub2e8\uc2dd", "landPriceMaxByPtp": {"ptpNo": "1", "supplyArea": "55.78", "totalArea": "55.78", "minPrice": "325000000", "maxPrice": "343000000", "stdYear": 2019, "stdYmd": "20190101", "landPriceTax": {"propertyTotalTax": 689520, "propertyTax": 334500, "localEduTax": 66900, "cityAreaTax": 288120, "realEstateTotalTax": 0, "decisionTax": 0, "ruralSpecialTax": 0}}, "roomCnt": "3", "bathroomCnt": "2"}, {"pyeongNo": "2", "supplyAreaDouble": 55.81, "supplyArea": "55.81", "pyeongName": "55B", "supplyPyeong": "16.88", "pyeongName2": "16B", "exclusiveArea": "45.33", "exclusivePyeong": "13.71", "householdCountByPyeong": "4", "realEstateTypeCode": "A01", "exclusiveRate": "81", "articleStatistics": {"pyeongNo": "2", "dealCount": "0", "leaseCount": "0", "rentCount": "1", "shortTermRentCount": "0", "dealPriceString": "", "dealPricePerSpaceString": "", "leasePriceString": "", "leasePricePerSpaceString": "", "leasePriceRateString": "", "rentPriceString": "5,000/220", "rentDepositPriceMin": "5,000", "rentPriceMin": "220", "rentDepositPriceMax": "5,000", "rentPriceMax": "220"}, "entranceType": "\uacc4\ub2e8\uc2dd", "landPriceMaxByPtp": {"ptpNo": "2", "supplyArea": "55.81", "totalArea": "55.81", "minPrice": "325000000", "maxPrice": "343000000", "stdYear": 2019, "stdYmd": "20190101", "landPriceTax": {"propertyTotalTax": 689520, "propertyTax": 334500, "localEduTax": 66900, "cityAreaTax": 288120, "realEstateTotalTax": 0, "decisionTax": 0, "ruralSpecialTax": 0}}, "roomCnt": "3", "bathroomCnt": "2"}, {"pyeongNo": "3", "supplyAreaDouble": 55.82, "supplyArea": "55.82", "pyeongName": "55C", "supplyPyeong": "16.88", "pyeongName2": "16C", "exclusiveArea": "45.34", "exclusivePyeong": "13.71", "householdCountByPyeong": "4", "realEstateTypeCode": "A01", "exclusiveRate": "81", "articleStatistics": {"pyeongNo": "3", "dealCount": "6", "leaseCount": "0", "rentCount": "2", "shortTermRentCount": "0", "dealPriceMin": "7\uc5b5 3,000", "dealPriceMax": "7\uc5b5 7,000", "dealPricePerSpaceMin": "4,323", "dealPricePerSpaceMax": "4,560", "dealPriceString": "7\uc5b5 3,000~7\uc5b5 7,000", "dealPricePerSpaceString": "(4,323~4,560\ub9cc\uc6d0/3.3\u33a1)", "leasePriceString": "", "leasePricePerSpaceString": "", "leasePriceRateString": "", "rentPriceString": "1\uc5b5/195~1\uc5b5/200", "rentDepositPriceMin": "1\uc5b5", "rentPriceMin": "195", "rentDepositPriceMax": "1\uc5b5", "rentPriceMax": "200"}, "entranceType": "\uacc4\ub2e8\uc2dd", "landPriceMaxByPtp": {"ptpNo": "3", "supplyArea": "55.82", "totalArea": "55.82", "minPrice": "325000000", "maxPrice": "343000000", "stdYear": 2019, "stdYmd": "20190101", "landPriceTax": {"propertyTotalTax": 689520, "propertyTax": 334500, "localEduTax": 66900, "cityAreaTax": 288120, "realEstateTotalTax": 0, "decisionTax": 0, "ruralSpecialTax": 0}}, "roomCnt": "3", "bathroomCnt": "2"}]}