{"photos": [], "complexDetail": {"complexNo": "115616", "complexName": "\uc6d4\ud2bc\ud30c\ud06c\ubdf0", "cortarNo": "1123010600", "realEstateTypeCode": "OPST", "realEstateTypeName": "\uc624\ud53c\uc2a4\ud154", "detailAddress": "342-21", "roadAddress": "\uc7a5\ud55c\ub85c26\ub098\uae38 3", "latitude": 37.571366, "longitude": 127.072994, "totalHouseholdCount": 9, "totalLeaseHouseholdCount": 0, "permanentLeaseHouseholdCount": 0, "nationLeaseHouseholdCount": 0, "civilLeaseHouseholdCount": 0, "publicLeaseHouseholdCount": 0, "longTermLeaseHouseholdCount": 0, "etcLeaseHouseholdCount": 0, "highFloor": 4, "lowFloor": 4, "completionYearMonth": "201611", "totalDongCount": 1, "maxSupplyArea": 96.6, "minSupplyArea": 79.93, "dealCount": 0, "rentCount": 0, "leaseCount": 0, "shortTermRentCount": 0, "isBookmarked": false, "batlRatio": "599", "btlRatio": "59", "parkingCountByHousehold": 0.77, "constructionCompanyName": "\uc8fc\uc2dd\ud68c\uc0ac\ub9c8\uc131", "heatMethodTypeCode": "HT001", "heatFuelTypeCode": "HF001", "pyoengNames": "79\u33a1, 94\u33a1, 96", "address": "\uc11c\uc6b8\uc2dc \ub3d9\ub300\ubb38\uad6c \uc7a5\uc548\ub3d9", "roadAddressPrefix": "\uc11c\uc6b8\uc2dc \ub3d9\ub300\ubb38\uad6c"}, "complexPyeongDetailList": [{"pyeongNo": "1", "supplyAreaDouble": 79.93, "supplyArea": "79.93", "pyeongName": "79", "supplyPyeong": "24.17", "pyeongName2": "24", "exclusiveArea": "59.98", "exclusivePyeong": "18.14", "householdCountByPyeong": "3", "realEstateTypeCode": "A02", "exclusiveRate": "75", "entranceType": "\uacc4\ub2e8\uc2dd", "roomCnt": "3", "bathroomCnt": "1"}, {"pyeongNo": "2", "supplyAreaDouble": 94.61, "supplyArea": "94.61", "pyeongName": "94", "supplyPyeong": "28.61", "pyeongName2": "28", "exclusiveArea": "71.01", "exclusivePyeong": "21.48", "householdCountByPyeong": "3", "realEstateTypeCode": "A02", "exclusiveRate": "75", "entranceType": "\uacc4\ub2e8\uc2dd", "roomCnt": "3", "bathroomCnt": "2"}, {"pyeongNo": "3", "supplyAreaDouble": 96.6, "supplyArea": "96.6", "pyeongName": "96", "supplyPyeong": "29.22", "pyeongName2": "29", "exclusiveArea": "72.5", "exclusivePyeong": "21.93", "householdCountByPyeong": "3", "realEstateTypeCode": "A02", "exclusiveRate": "75", "entranceType": "\uacc4\ub2e8\uc2dd", "roomCnt": "3", "bathroomCnt": "2"}]}