{"photos": [], "complexDetail": {"complexNo": "121785", "complexName": "\uc2a4\ud0c0\ud0c0\uc6b4", "cortarNo": "1138010600", "realEstateTypeCode": "APT", "realEstateTypeName": "\uc544\ud30c\ud2b8", "detailAddress": "186-10", "roadAddress": "\ud1b5\uc77c\ub85c 827-8", "latitude": 37.617488, "longitude": 126.922026, "totalHouseholdCount": 8, "totalLeaseHouseholdCount": 0, "permanentLeaseHouseholdCount": 0, "nationLeaseHouseholdCount": 0, "civilLeaseHouseholdCount": 0, "publicLeaseHouseholdCount": 0, "longTermLeaseHouseholdCount": 0, "etcLeaseHouseholdCount": 0, "highFloor": 11, "lowFloor": 11, "completionYearMonth": "201807", "totalDongCount": 1, "maxSupplyArea": 35.26, "minSupplyArea": 35.06, "dealCount": 0, "rentCount": 0, "leaseCount": 0, "shortTermRentCount": 0, "isBookmarked": false, "batlRatio": "425", "btlRatio": "58", "parkingCountByHousehold": 0.62, "constructionCompanyName": "(\uc8fc)\ub300\uc2e0\uc885\ud569\uac74\uc124", "heatMethodTypeCode": "HT001", "heatFuelTypeCode": "HF001", "pyoengNames": "35A\u33a1, 35B", "address": "\uc11c\uc6b8\uc2dc \uc740\ud3c9\uad6c \ub300\uc870\ub3d9", "roadAddressPrefix": "\uc11c\uc6b8\uc2dc \uc740\ud3c9\uad6c"}, "complexPyeongDetailList": [{"pyeongNo": "1", "supplyAreaDouble": 35.06, "supplyArea": "35.06", "pyeongName": "35A", "supplyPyeong": "10.6", "pyeongName2": "10A", "exclusiveArea": "22.98", "exclusivePyeong": "6.95", "householdCountByPyeong": "4", "realEstateTypeCode": "A03", "exclusiveRate": "66", "entranceType": "\uacc4\ub2e8\uc2dd", "roomCnt": "1", "bathroomCnt": "1"}, {"pyeongNo": "2", "supplyAreaDouble": 35.26, "supplyArea": "35.26", "pyeongName": "35B", "supplyPyeong": "10.66", "pyeongName2": "10B", "exclusiveArea": "23.1", "exclusivePyeong": "6.98", "householdCountByPyeong": "4", "realEstateTypeCode": "A03", "exclusiveRate": "66", "entranceType": "\uacc4\ub2e8\uc2dd", "roomCnt": "1", "bathroomCnt": "1"}]}